tests/__init__.py
tests/test_all.py
text2numde/__init__.py
text2numde/text2numde.py
text2numde-1.0.dist-info/LICENSE
text2numde-1.0.dist-info/METADATA
text2numde-1.0.dist-info/WHEEL
text2numde-1.0.dist-info/top_level.txt
text2numde-1.0.dist-info/RECORD
