Metadata-Version: 2.1
Name: text2numde
Version: 1.0
Summary: This library converts German numbers written as text to integer and float values.
Home-page: https://github.com/padmalcom/text2numde
Author: Jonas Freiknecht
Author-email: j.freiknecht@googlemail.com
License: UNKNOWN
Platform: UNKNOWN
Classifier: Development Status :: 5 - Production/Stable
Classifier: License :: OSI Approved :: MIT License
Classifier: Operating System :: OS Independent
Requires-Python: >=3.6
